feeluown/__init__.py
feeluown/__main__.py
feeluown/ai.py
feeluown/alert.py
feeluown/argparser.py
feeluown/collection.py
feeluown/config.py
feeluown/consts.py
feeluown/excs.py
feeluown/media.py
feeluown/mpv.py
feeluown/plugin.py
feeluown/task.py
feeluown/version.py
feeluown/app/__init__.py
feeluown/app/app.py
feeluown/app/cli_app.py
feeluown/app/config.py
feeluown/app/gui_app.py
feeluown/app/mixed_app.py
feeluown/app/mode.py
feeluown/app/once_app.py
feeluown/app/server_app.py
feeluown/cli/__init__.py
feeluown/cli/cli.py
feeluown/cli/install.py
feeluown/entry_points/__init__.py
feeluown/entry_points/base.py
feeluown/entry_points/run.py
feeluown/entry_points/run_app.py
feeluown/entry_points/run_cli.py
feeluown/fuoexec/__init__.py
feeluown/fuoexec/functions.py
feeluown/fuoexec/fuoexec.py
feeluown/fuoexec/signal_manager.py
feeluown/gui/__init__.py
feeluown/gui/base_renderer.py
feeluown/gui/browser.py
feeluown/gui/consts.py
feeluown/gui/debug.py
feeluown/gui/drawers.py
feeluown/gui/helpers.py
feeluown/gui/hotkey.py
feeluown/gui/image.py
feeluown/gui/mimedata.py
feeluown/gui/provider_ui.py
feeluown/gui/theme.py
feeluown/gui/tips.py
feeluown/gui/tray.py
feeluown/gui/ui.py
feeluown/gui/watch.py
feeluown/gui/assets/icons/already_download.png
feeluown/gui/assets/icons/already_downloaded_dark.png
feeluown/gui/assets/icons/cur_playlist.png
feeluown/gui/assets/icons/cur_playlist_dark.png
feeluown/gui/assets/icons/download.png
feeluown/gui/assets/icons/download_dark.png
feeluown/gui/assets/icons/feeluown.icns
feeluown/gui/assets/icons/feeluown.ico
feeluown/gui/assets/icons/feeluown.png
feeluown/gui/assets/icons/like.png
feeluown/gui/assets/icons/like_checked.png
feeluown/gui/assets/icons/like_checked_dark.png
feeluown/gui/assets/icons/like_dark.png
feeluown/gui/assets/icons/tray-dark.png
feeluown/gui/assets/icons/tray-light.png
feeluown/gui/assets/themes/common.qss
feeluown/gui/assets/themes/dark.qss
feeluown/gui/assets/themes/light.qss
feeluown-4.1.10.dist-info/LICENSE
feeluown-4.1.10.dist-info/METADATA
feeluown-4.1.10.dist-info/WHEEL
feeluown-4.1.10.dist-info/entry_points.txt
feeluown-4.1.10.dist-info/top_level.txt
feeluown-4.1.10.dist-info/RECORD
