Metadata-Version: 2.1
Name: feeluown
Version: 4.1.10
Summary: *nix music player
Home-page: https://github.com/feeluown/FeelUOwn
Author: feeluown
Author-email: yinshaowen241@gmail.com
License: GPL-3.0
Keywords: media,player,application,PyQt5,music
Classifier: Programming Language :: Python :: 3.8
Classifier: Programming Language :: Python :: 3.9
Classifier: Programming Language :: Python :: 3.10
Classifier: Programming Language :: Python :: 3.11
Classifier: Programming Language :: Python :: 3.12
Classifier: Programming Language :: Python :: 3 :: Only
Classifier: Environment :: X11 Applications :: Qt
Classifier: Topic :: Multimedia :: Sound/Audio
Classifier: Operating System :: MacOS
Classifier: Operating System :: Microsoft :: Windows
Classifier: Operating System :: POSIX :: Linux
Classifier: License :: OSI Approved :: GNU General Public License v3 (GPLv3)
Requires-Python: >=3.8
License-File: LICENSE
Requires-Dist: janus
Requires-Dist: requests
Requires-Dist: qasync
Requires-Dist: tomlkit
Requires-Dist: packaging
Requires-Dist: pydantic (>=1.10)
Requires-Dist: mutagen (>=1.37)
Provides-Extra: ai
Requires-Dist: openai (>=1.50) ; extra == 'ai'
Provides-Extra: battery
Requires-Dist: fuo-netease (>=1.0.3) ; extra == 'battery'
Requires-Dist: fuo-qqmusic (>=1.0.5) ; extra == 'battery'
Requires-Dist: fuo-ytmusic (>=0.4.4) ; extra == 'battery'
Requires-Dist: feeluown-bilibili (>=0.4.1) ; extra == 'battery'
Provides-Extra: cookies
Requires-Dist: yt-dlp ; extra == 'cookies'
Provides-Extra: dev
Requires-Dist: flake8 ; extra == 'dev'
Requires-Dist: pylint ; extra == 'dev'
Requires-Dist: mypy ; extra == 'dev'
Requires-Dist: pyqt5-stubs ; extra == 'dev'
Requires-Dist: pytest (>=5.4.0) ; extra == 'dev'
Requires-Dist: pytest-runner ; extra == 'dev'
Requires-Dist: pytest-cov ; extra == 'dev'
Requires-Dist: pytest-asyncio ; extra == 'dev'
Requires-Dist: pytest-qt ; extra == 'dev'
Requires-Dist: pytest-mock ; extra == 'dev'
Requires-Dist: pytest-benchmark (>=3.4.1) ; extra == 'dev'
Requires-Dist: sphinx ; extra == 'dev'
Requires-Dist: sphinx-rtd-theme ; extra == 'dev'
Provides-Extra: macos
Requires-Dist: aionowplaying (>=0.10) ; extra == 'macos'
Provides-Extra: qt
Requires-Dist: PyQt5 ; extra == 'qt'
Provides-Extra: webengine
Requires-Dist: PyQtWebEngine ; extra == 'webengine'
Provides-Extra: webserver
Requires-Dist: sanic ; extra == 'webserver'
Requires-Dist: websockets ; extra == 'webserver'
Requires-Dist: json-rpc ; extra == 'webserver'
Provides-Extra: win32
Requires-Dist: pyshortcuts ; extra == 'win32'
Requires-Dist: aionowplaying (>=0.10) ; extra == 'win32'
Provides-Extra: ytdl
Requires-Dist: yt-dlp ; extra == 'ytdl'
